[
  {
    "title": "Movie 1",
    "year": 2020,
    "duration": 120,
    "comments": []
  },
  {
    "title": "Movie 2",
    "year": 2019,
    "duration": 115,
    "comments": []
  },
  {
    "title": "Movie 3",
    "year": 2018,
    "duration": 130,
    "comments": []
  },
  {
    "title": "Movie 4",
    "year": 2017,
    "duration": 110,
    "comments": []
  },
  {
    "title": "Movie 5",
    "year": 2016,
    "duration": 105,
    "comments": []
  },
  {
    "title": "Movie 6",
    "year": 2015,
    "duration": 140,
    "comments": []
  },
  {
    "title": "Movie 7",
    "year": 2014,
    "duration": 125,
    "comments": []
  },
  {
    "title": "Movie 8",
    "year": 2013,
    "duration": 135,
    "comments": []
  },
  {
    "title": "Movie 9",
    "year": 2012,
    "duration": 100,
    "comments": []
  },
  {
    "title": "Movie 10",
    "year": 2011,
    "duration": 145,
    "comments": []
  }
]
